{
  "$schema": "https://raw.githubusercontent.com/AtomicBlom/ProjectTable/04156961c15aae03d32c3deeba340d2ad6021636/src/main/resources/projectTableRecipe.schema.json",
  "crafts": [
    {
      "id": "minecraft:stained_glass",
      "Count": 8,
      "Damage": 3
    }
  ],
  "ingredients": [
    {
      "oredict": "blockGlassColorless",
      "Count": 8,
      "tool": false,
      "durabilityCost": 1
    },
    {
      "oredict": "dyeLightBlue",
      "Count": 1,
      "tool": false,
      "durabilityCost": 1
    }
  ]
}